monobox/__init__.py
monobox/main.py
monobox-0.4.1.dist-info/METADATA
monobox-0.4.1.dist-info/RECORD
monobox-0.4.1.dist-info/WHEEL
monobox-0.4.1.dist-info/entry_points.txt
monobox-0.4.1.dist-info/top_level.txt
