Metadata-Version: 2.1
Name: monobox
Version: 0.4.1
Summary: A uniform flexible environment for coding, testing, and deploying using Docker
Home-page: https://github.com/InnovativeInventor/monobox
Author: InnovativeInventor
Author-email: theinnovativeinventor@gmail.com
License: UNKNOWN
Project-URL: Bug Reports, https://github.com/InnovativeInventor/monobox/issues
Project-URL: Source, https://github.com/InnovativeInventor/monobox
Keywords: monobox docker development
Platform: UNKNOWN
Classifier: Development Status :: 3 - Alpha
Classifier: Programming Language :: Python :: 3
Classifier: Intended Audience :: Developers
Classifier: Topic :: Software Development :: Build Tools
Classifier: License :: OSI Approved :: MIT License
Classifier: Programming Language :: Python :: 3.4
Classifier: Programming Language :: Python :: 3.5
Classifier: Programming Language :: Python :: 3.6
Classifier: Programming Language :: Python :: 3.7
Requires-Dist: docker
Requires-Dist: requests
Requires-Dist: click
